odoo/addons/l10n_fr_chorus_sale/README.rst
odoo/addons/l10n_fr_chorus_sale/__init__.py
odoo/addons/l10n_fr_chorus_sale/__manifest__.py
odoo/addons/l10n_fr_chorus_sale/i18n/es.po
odoo/addons/l10n_fr_chorus_sale/i18n/fr.po
odoo/addons/l10n_fr_chorus_sale/i18n/l10n_fr_chorus_sale.pot
odoo/addons/l10n_fr_chorus_sale/models/__init__.py
odoo/addons/l10n_fr_chorus_sale/models/sale_order.py
odoo/addons/l10n_fr_chorus_sale/readme/CONTRIBUTORS.md
odoo/addons/l10n_fr_chorus_sale/readme/DESCRIPTION.md
odoo/addons/l10n_fr_chorus_sale/readme/USAGE.md
odoo/addons/l10n_fr_chorus_sale/static/description/icon.png
odoo/addons/l10n_fr_chorus_sale/static/description/index.html
odoo/addons/l10n_fr_chorus_sale/views/sale_order.xml
odoo_addon_l10n_fr_chorus_sale-18.0.1.0.0.5.dist-info/METADATA
odoo_addon_l10n_fr_chorus_sale-18.0.1.0.0.5.dist-info/WHEEL
odoo_addon_l10n_fr_chorus_sale-18.0.1.0.0.5.dist-info/top_level.txt
odoo_addon_l10n_fr_chorus_sale-18.0.1.0.0.5.dist-info/RECORD
