Metadata-Version: 2.1
Name: odoo-addon-l10n_fr_chorus_sale
Version: 18.0.1.0.0.5
Requires-Python: >=3.10
Requires-Dist: odoo-addon-l10n_fr_chorus_account==18.0.*
Requires-Dist: odoo==18.0.*
Summary: Add checks on sale orders for Chorus Pro
Home-page: https://github.com/OCA/l10n-france
License: AGPL-3
Author: Akretion,Odoo Community Association (OCA)
Author-email: support@odoo-community.org
Classifier: Programming Language :: Python
Classifier: Framework :: Odoo
Classifier: Framework :: Odoo :: 18.0
Classifier: License :: OSI Approved :: GNU Affero General Public License v3
